setup.py
QuarkUtilities.egg-info/PKG-INFO
QuarkUtilities.egg-info/SOURCES.txt
QuarkUtilities.egg-info/dependency_links.txt
QuarkUtilities.egg-info/requires.txt
QuarkUtilities.egg-info/top_level.txt
quark_utilities/__init__.py
quark_utilities/custom_id_generator.py
quark_utilities/db.py
quark_utilities/dict_helpers.py
quark_utilities/email_sender.py
quark_utilities/errors.py
quark_utilities/event_hub.py
quark_utilities/events.py
quark_utilities/ip2location_helpers.py
quark_utilities/json_helpers.py
quark_utilities/json_schema.py
quark_utilities/jwt_security.py
quark_utilities/mongol.py
quark_utilities/query_helpers.py
quark_utilities/responser.py
quark_utilities/rest.py
quark_utilities/secret_utils.py
quark_utilities/temporal_helpers.py
quark_utilities/webhook.py
quark_utilities/commons/__init__.py
quark_utilities/commons/error_handlers.py
test/test_generic_repository.py
test/test_sm.py